fem_assignments/problem1_seq_detect/seq_detect_mealy.v
`timescale 1ns / 1ps

module seq_detect_mealy(
    input  din,
    input  clk,
    input  rst,
    output y
    );    
    reg [1:0] current_state, next_state;
    parameter S0 = 2'd0,  // no match
              S1 = 2'd1,  // '1'
              S2 = 2'd2,  // "11"
              S3 = 2'd3;  // "110"
    
    always @(posedge clk)        
    begin
        if (rst)                    
            current_state <= S0;
        else
            current_state <= next_state;  
    end    
    always @(*)                   
    begin
        case (current_state)
            S0: if (!(din)) next_state = S0; else next_state = S1;
        
            S1: if (!(din)) next_state = S0; else next_state = S2;
                    
            S2: if (!(din)) next_state = S3; else next_state = S2;
                    
            S3: if (!(din)) next_state = S0; else next_state = S1;
       
            default: next_state = S0; 
        endcase
    end
    assign y = (current_state == S3) & din; 
endmodule

fem_assignments/problem1_seq_detect/tb_seq_detect_mealy.v
`timescale 1ns / 1ps

module tb_seq_detect_mealy;

	reg clk;
	reg rst;
	reg din;
	wire y;

	seq_detect_mealy dut (
		.din(din),
		.clk(clk),
		.rst(rst),
		.y(y)
	);

	initial clk = 0;
	always #5 clk = ~clk;

	initial begin
		$dumpfile("waveform.vcd");
		$dumpvars(0, tb_seq_detect_mealy);

		rst = 1;
		din = 0;
		@(posedge clk);
		@(posedge clk);
		rst = 0;

		din=1; @(posedge clk);
		din=1; @(posedge clk);
		din=0; @(posedge clk);
		din=1; @(posedge clk);

		din=0; @(posedge clk);

		din=1; @(posedge clk);
		din=1; @(posedge clk);
		din=0; @(posedge clk);
		din=1; @(posedge clk);
		din=1; @(posedge clk);
		din=0; @(posedge clk);
		din=1; @(posedge clk);

		din=0; @(posedge clk);

		din=0; @(posedge clk);
		din=1; @(posedge clk);
		din=1; @(posedge clk);
		din=0; @(posedge clk);
		din=1; @(posedge clk);
		din=1; @(posedge clk);
		din=0; @(posedge clk);
		din=1; @(posedge clk);

		din=1; @(posedge clk);
		din=1; @(posedge clk);
		din=1; @(posedge clk);
		din=1; @(posedge clk);
		din=0; @(posedge clk);
		din=1; @(posedge clk);

		#20;
		$display("\n[TB] Simulation finished.");
		$finish;
	end

endmodule

fem_assignments/problem1_seq_detect/waveform.vcd
$date
	Tue Aug 19 12:37:39 2025
$end
$version
	Icarus Verilog
$end
$timescale
	1ps
$end
$scope module tb_seq_detect_mealy $end
$var wire 1 ! y $end
$var reg 1 " clk $end
$var reg 1 # din $end
$var reg 1 $ rst $end
$scope module dut $end
$var wire 1 " clk $end
$var wire 1 # din $end
$var wire 1 $ rst $end
$var wire 1 ! y $end
$var parameter 2 % S0 $end
$var parameter 2 & S1 $end
$var parameter 2 ' S2 $end
$var parameter 2 ( S3 $end
$var reg 2 ) current_state [1:0] $end
$var reg 2 * next_state [1:0] $end
$upscope $end
$upscope $end
$enddefinitions $end
$comment Show the parameter values. $end
$dumpall
b11 (
b10 '
b1 &
b0 %
$end
#0
$dumpvars
b0 *
bx )
1$
0#
0"
0!
$end
#5000
b0 )
1"
#10000
0"
#15000
b1 *
1#
0$
1"
#20000
0"
#25000
b10 *
b1 )
1"
#30000
0"
#35000
b10 )
b11 *
0#
1"
#40000
0"
#45000
1!
b11 )
b1 *
1#
1"
#50000
0"
#55000
b1 )
0!
b0 *
0#
1"
#60000
0"
#65000
b0 )
b1 *
1#
1"
#70000
0"
#75000
b10 *
b1 )
1"
#80000
0"
#85000
b10 )
b11 *
0#
1"
#90000
0"
#95000
1!
b11 )
b1 *
1#
1"
#100000
0"
#105000
b10 *
0!
b1 )
1"
#110000
0"
#115000
b10 )
b11 *
0#
1"
#120000
0"
#125000
1!
b11 )
b1 *
1#
1"
#130000
0"
#135000
b1 )
0!
b0 *
0#
1"
#140000
0"
#145000
b0 )
1"
#150000
0"
#155000
b1 *
1#
1"
#160000
0"
#165000
b10 *
b1 )
1"
#170000
0"
#175000
b10 )
b11 *
0#
1"
#180000
0"
#185000
1!
b11 )
b1 *
1#
1"
#190000
0"
#195000
b10 *
0!
b1 )
1"
#200000
0"
#205000
b10 )
b11 *
0#
1"
#210000
0"
#215000
1!
b11 )
b1 *
1#
1"
#220000
0"
#225000
b10 *
0!
b1 )
1"
#230000
0"
#235000
b10 )
1"
#240000
0"
#245000
1"
#250000
0"
#255000
1"
#260000
0"
#265000
b11 *
0#
1"
#270000
0"
#275000
1!
b11 )
b1 *
1#
1"
#280000
0"
#285000
b10 *
0!
b1 )
1"
#290000
0"
#295000
b10 )
1"
