fem_assignments/problem4_link/slave_fsm.v
`timescale 1ns / 1ps
module slave_fsm(
    input  wire clk_sig,
    input  wire rst_n,
    input  wire req_in,
    input  wire [7:0] data_bus_in,
    output reg  ack_out,
    output reg  [7:0] last_data
);

    localparam ST_IDLE   = 2'b00,
               ST_ACK1   = 2'b01,
               ST_ACK2   = 2'b10,
               ST_WAIT   = 2'b11;

    reg [1:0] cur_st, next_st;

    always @(posedge clk_sig) begin
        if (rst_n) begin
            cur_st   <= ST_IDLE;
            last_data <= 8'b0;
        end else begin
            cur_st <= next_st;
            if (cur_st == ST_IDLE && req_in) begin
                last_data <= data_bus_in;
            end
        end
    end

    always @(*) begin
        next_st = cur_st;
        ack_out = 1'b0;

        case (cur_st)
            ST_IDLE: if (req_in) next_st = ST_ACK1;

            ST_ACK1: begin
                ack_out = 1'b1;
                next_st = ST_ACK2;
            end

            ST_ACK2: begin
                ack_out = 1'b1;
                next_st = ST_WAIT;
            end

            ST_WAIT: begin
                if (!req_in) next_st = ST_IDLE;
            end
        endcase
    end
endmodule

fem_assignments/problem4_link/master_fsm.v
`timescale 1ns / 1ps
module master_fsm(
    input  wire clk_sig,
    input  wire rst_n,
    input  wire ack_in,
    output reg  req_out,
    output reg  [7:0] data_bus,
    output reg  finished
);

    localparam ST_IDLE       = 3'b000,
               ST_SEND       = 3'b001,
               ST_WAIT_ACK   = 3'b010,
               ST_WAIT_LOW   = 3'b011,
               ST_DONE       = 3'b100;

    reg [2:0] cur_st, next_st;
    reg [1:0] byte_cnt, byte_cnt_next;

    always @(posedge clk_sig) begin
        if (rst_n) begin
            cur_st   <= ST_IDLE;
            byte_cnt <= 2'b00;
        end else begin
            cur_st   <= next_st;
            byte_cnt <= byte_cnt_next;
        end
    end

    always @(*) begin
        next_st       = cur_st;
        byte_cnt_next = byte_cnt;
        req_out       = 1'b0;
        data_bus      = 8'hZZ;
        finished      = 1'b0;

        case (cur_st)
            ST_IDLE: next_st = ST_SEND;

            ST_SEND: begin
                req_out  = 1'b1;
                data_bus = 8'hA0 + byte_cnt;
                next_st  = ST_WAIT_ACK;
            end

            ST_WAIT_ACK: begin
                data_bus = 8'hA0 + byte_cnt;
                if (ack_in) begin
                    next_st  = ST_WAIT_LOW;
                    req_out  = 1'b0;
                end
            end

            ST_WAIT_LOW: begin
                if (!ack_in) begin
                    if (byte_cnt == 2'd3) next_st = ST_DONE;
                    else begin
                        next_st       = ST_SEND;
                        byte_cnt_next = byte_cnt + 1;
                    end
                end
            end

            ST_DONE: begin
                finished = 1'b1;
                next_st  = ST_IDLE;
            end
        endcase
    end

endmodule

fem_assignments/problem4_link/link_top.v
`timescale 1ns / 1ps
module link_top(
    input  wire clk_sig,
    input  wire rst_n,
    output wire finished
);

    wire req_sig, ack_sig;
    wire [7:0] data_bus;

    master_fsm u_master (
        .clk_sig(clk_sig),
        .rst_n(rst_n),
        .ack_in(ack_sig),
        .req_out(req_sig),
        .data_bus(data_bus),
        .finished(finished)
    );

    slave_fsm u_slave (
        .clk_sig(clk_sig),
        .rst_n(rst_n),
        .req_in(req_sig),
        .data_bus_in(data_bus),
        .ack_out(ack_sig),
        .last_data()
    );

endmodule

fem_assignments/problem4_link/tb_link_top.v
`timescale 1ns / 1ps
module tb_link_top;
    parameter CLK_PERIOD = 10;
    reg clk_sig, rst_n;
    wire finished;

    link_top dut (.clk_sig(clk_sig), .rst_n(rst_n), .finished(finished));

    initial begin
        clk_sig = 0;
        forever #(CLK_PERIOD / 2) clk_sig = ~clk_sig;
    end

    initial begin
        $dumpfile("waveform.vcd");
        $dumpvars(0, tb_link_top);

        rst_n = 1;
        repeat(2) @(posedge clk_sig);
        rst_n = 0;

        wait (finished);
        @(posedge clk_sig);
        $display("4-byte transfer complete at time %0t ns.", $time);
        $finish;
    end
endmodule

fem_assignments/problem4_link/waveform.vcd
$date
	Tue Aug 19 12:10:05 2025
$end
$version
	Icarus Verilog
$end
$timescale
	1ps
$end
$scope module tb_link_top $end
$var wire 1 ! finished $end
$var parameter 32 " CLK_PERIOD $end
$var reg 1 # clk_sig $end
$var reg 1 $ rst_n $end
$scope module dut $end
$var wire 1 # clk_sig $end
$var wire 1 $ rst_n $end
$var wire 1 % req_sig $end
$var wire 1 ! finished $end
$var wire 8 & data_bus [7:0] $end
$var wire 1 ' ack_sig $end
$scope module u_master $end
$var wire 1 # clk_sig $end
$var wire 1 $ rst_n $end
$var wire 1 ' ack_in $end
$var parameter 3 ( ST_DONE $end
$var parameter 3 ) ST_IDLE $end
$var parameter 3 * ST_SEND $end
$var parameter 3 + ST_WAIT_ACK $end
$var parameter 3 , ST_WAIT_LOW $end
$var reg 2 - byte_cnt [1:0] $end
$var reg 2 . byte_cnt_next [1:0] $end
$var reg 3 / cur_st [2:0] $end
$var reg 8 0 data_bus [7:0] $end
$var reg 1 ! finished $end
$var reg 3 1 next_st [2:0] $end
$var reg 1 % req_out $end
$upscope $end
$scope module u_slave $end
$var wire 1 # clk_sig $end
$var wire 8 2 data_bus_in [7:0] $end
$var wire 1 % req_in $end
$var wire 1 $ rst_n $end
$var parameter 2 3 ST_ACK1 $end
$var parameter 2 4 ST_ACK2 $end
$var parameter 2 5 ST_IDLE $end
$var parameter 2 6 ST_WAIT $end
$var reg 1 ' ack_out $end
$var reg 2 7 cur_st [1:0] $end
$var reg 8 8 last_data [7:0] $end
$var reg 2 9 next_st [1:0] $end
$upscope $end
$upscope $end
$upscope $end
$enddefinitions $end
$comment Show the parameter values. $end
$dumpall
b11 6
b0 5
b10 4
b1 3
b11 ,
b10 +
b1 *
b0 )
b100 (
b1010 "
$end
#0
$dumpvars
bx 9
bx 8
bx 7
bx 2
bx 1
bx 0
bx /
bx .
bx -
x'
bx &
x%
1$
0#
x!
$end
#5000
0!
bz &
bz 0
bz 2
0%
b0 .
b1 1
0'
b0 9
b0 -
b0 /
b0 8
b0 7
1#
#10000
0#
#15000
0$
1#
#20000
0#
#25000
b1 9
b10 1
b10100000 &
b10100000 0
b10100000 2
1%
b1 /
1#
#30000
0#
#35000
b11 1
b10 9
1'
b10100000 &
b10100000 0
b10100000 2
0%
b10100000 8
b1 7
b10 /
1#
#40000
0#
#45000
bz &
bz 0
bz 2
b11 9
1'
b11 /
b10 7
1#
#50000
0#
#55000
b1 .
b1 1
b0 9
0'
b11 7
1#
#60000
0#
#65000
b1 9
b10 1
b10100001 &
b10100001 0
b10100001 2
1%
b1 -
b1 /
b0 7
1#
#70000
0#
#75000
b11 1
b10 9
1'
b10100001 &
b10100001 0
b10100001 2
0%
b10100001 8
b1 7
b10 /
1#
#80000
0#
#85000
bz &
bz 0
bz 2
b11 9
1'
b11 /
b10 7
1#
#90000
0#
#95000
b10 .
b1 1
b0 9
0'
b11 7
1#
#100000
0#
#105000
b1 9
b10 1
b10100010 &
b10100010 0
b10100010 2
1%
b10 -
b1 /
b0 7
1#
#110000
0#
#115000
b11 1
b10 9
1'
b10100010 &
b10100010 0
b10100010 2
0%
b10100010 8
b1 7
b10 /
1#
#120000
0#
#125000
bz &
bz 0
bz 2
b11 9
1'
b11 /
b10 7
1#
#130000
0#
#135000
b11 .
b1 1
b0 9
0'
b11 7
1#
#140000
0#
#145000
b1 9
b10 1
b10100011 &
b10100011 0
b10100011 2
1%
b11 -
b1 /
b0 7
1#
#150000
0#
#155000
b11 1
b10 9
1'
b10100011 &
b10100011 0
b10100011 2
0%
b10100011 8
b1 7
b10 /
1#
#160000
0#
#165000
bz &
bz 0
bz 2
b11 9
1'
b11 /
b10 7
1#
#170000
0#
#175000
b100 1
b0 9
0'
b11 7
1#
#180000
0#
#185000
b0 1
1!
b100 /
b0 7
1#
#190000
0#
#195000
b1 1
0!
b0 /
1#
