fem_assignments/problem3_vending/vending_mealy.v
`timescale 1ns / 1ps
module vending_mealy(
    input  wire clk_sig,
    input  wire reset,
    input  wire [1:0] coin_in,
    output wire item_out,
    output wire return5
);
    reg [1:0] st_cur, st_nxt;

    parameter S_IDLE  = 2'd0,  
              S_5     = 2'd1,  
              S_10    = 2'd2,  
              S_15    = 2'd3;  

    always @(posedge clk_sig) begin
        if (reset)
            st_cur <= S_IDLE;
        else
            st_cur <= st_nxt; 
    end

    always @(*) begin
        case (st_cur)
            S_IDLE: begin
                if (coin_in == 2'b00)
                    st_nxt = S_IDLE;
                else if (coin_in == 2'b01)
                    st_nxt = S_5;
                else
                    st_nxt = S_10;
            end
            S_5: begin
                if (coin_in == 2'b00)
                    st_nxt = S_IDLE;
                else if (coin_in == 2'b01)
                    st_nxt = S_10;
                else
                    st_nxt = S_15;
            end
            S_10: begin
                if (coin_in == 2'b00)
                    st_nxt = S_IDLE;
                else if (coin_in == 2'b01)
                    st_nxt = S_15;
                else
                    st_nxt = S_IDLE;
            end
            S_15: begin
                st_nxt = S_IDLE;
            end
        endcase
    end

    assign item_out = ( (st_cur == S_10  && coin_in == 2'b10) || 
                        (st_cur == S_15 && coin_in == 2'b01) || 
                        (st_cur == S_15 && coin_in == 2'b10) );

    assign return5 = (st_cur == S_15 && coin_in == 2'b10);

endmodule

fem_assignments/problem3_vending/tb_vending_mealy.v
`timescale 1ns / 1ps
module tb_vending_mealy();
    reg clk;
    reg reset;
    reg [1:0] coin_in;
    wire item_out;
    wire return5;

    vending_mealy dut (
        .clk_sig(clk),
        .reset(reset),
        .coin_in(coin_in),
        .item_out(item_out),
        .return5(return5)
    );

    initial clk = 0;
    always #5 clk = ~clk;

    initial begin
        $dumpfile("waveform.vcd");
        $dumpvars(0, tb_vending_mealy);

        reset = 1; coin_in = 2'b00;
        #20;
        reset = 0;

        @(posedge clk); coin_in = 2'b01;
        @(posedge clk); coin_in = 2'b01;
        @(posedge clk); coin_in = 2'b10;
        @(posedge clk); coin_in = 2'b00;
        repeat(2) @(posedge clk); coin_in = 2'b10;
        @(posedge clk); coin_in = 2'b10;
        @(posedge clk); coin_in = 2'b01;
        @(posedge clk); coin_in = 2'b00;
        repeat(2) @(posedge clk); coin_in = 2'b01;
        @(posedge clk); coin_in = 2'b00;
        @(posedge clk); coin_in = 2'b10;
        @(posedge clk); coin_in = 2'b01;
        @(posedge clk); coin_in = 2'b10;

        #50;
        $finish;
    end
endmodule

fem_assignments/problem3_vending/waveform.vcd
$date
	Tue Aug 19 13:50:47 2025
$end
$version
	Icarus Verilog
$end
$timescale
	1ps
$end
$scope module tb_vending_mealy $end
$var wire 1 ! return5 $end
$var wire 1 " item_out $end
$var reg 1 # clk $end
$var reg 2 $ coin_in [1:0] $end
$var reg 1 % reset $end
$scope module dut $end
$var wire 1 # clk_sig $end
$var wire 2 & coin_in [1:0] $end
$var wire 1 " item_out $end
$var wire 1 % reset $end
$var wire 1 ! return5 $end
$var parameter 2 ' S_10 $end
$var parameter 2 ( S_15 $end
$var parameter 2 ) S_5 $end
$var parameter 2 * S_IDLE $end
$var reg 2 + st_cur [1:0] $end
$var reg 2 , st_nxt [1:0] $end
$upscope $end
$upscope $end
$enddefinitions $end
$comment Show the parameter values. $end
$dumpall
b0 *
b1 )
b11 (
b10 '
$end
#0
$dumpvars
bx ,
bx +
b0 &
1%
b0 $
0#
0"
0!
$end
#5000
b0 ,
b0 +
1#
#10000
0#
#15000
1#
#20000
0#
0%
#25000
b1 ,
b1 $
b1 &
1#
#30000
0#
#35000
b10 ,
b1 +
1#
#40000
0#
#45000
1"
b10 +
b0 ,
b10 $
b10 &
1#
#50000
0#
#55000
b0 +
0"
b0 $
b0 &
1#
#60000
0#
#65000
1#
#70000
0#
#75000
b10 ,
b10 $
b10 &
1#
#80000
0#
#85000
1"
b0 ,
b10 +
1#
#90000
0#
#95000
b0 +
0"
b1 ,
b1 $
b1 &
1#
#100000
0#
#105000
b1 +
b0 ,
b0 $
b0 &
1#
#110000
0#
#115000
b0 +
1#
#120000
0#
#125000
b1 ,
b1 $
b1 &
1#
#130000
0#
#135000
b1 +
b0 ,
b0 $
b0 &
1#
#140000
0#
#145000
b0 +
b10 ,
b10 $
b10 &
1#
#150000
0#
#155000
b10 +
b11 ,
b1 $
b1 &
1#
#160000
0#
#165000
1!
b11 +
1"
b0 ,
b10 $
b10 &
1#
#170000
0#
#175000
0"
b10 ,
0!
b0 +
1#
#180000
0#
#185000
1"
b0 ,
b10 +
1#
#190000
0#
#195000
0"
b10 ,
b0 +
1#
#200000
0#
#205000
1"
b0 ,
b10 +
1#
#210000
0#
#215000
0"
b10 ,
b0 +
1#
